[
  {
    "title": "Gagner un salaire US en vivant en France, mythe ou réalité ?",
    "weight": "2",
    "source": "https://reddit.com/comments/1o3cbl9"
  },
  {
    "title": "Étudiant en école de commerce devenu dev autodidacte : quelle légitimité pour continuer dans ce domaine ?",
    "weight": "1",
    "source": "https://reddit.com/comments/1o2y310"
  },
  {
    "title": "On review vos CVs dev en live, chaque semaine sur Discord",
    "weight": "1",
    "source": "https://reddit.com/comments/1o1du0h"
  },
  {
    "title": "Développeur et Burn-out",
    "weight": "1",
    "source": "https://reddit.com/comments/1o2l49i"
  },
  {
    "title": "[MegaThread] Questions formation/Marché du travail",
    "weight": "1",
    "source": "https://reddit.com/comments/1o09lf4"
  }
]