[
  {
    "title": "Vous en pensez quoi de ce ESN?",
    "weight": "2",
    "source": "https://reddit.com/comments/1rbpqpx"
  },
  {
    "title": "auto-entrepreneur dans la sauce",
    "weight": "2",
    "source": "https://reddit.com/comments/1r9svla"
  },
  {
    "title": "reflag ou ça passe",
    "weight": "2",
    "source": "https://reddit.com/comments/1r95p7d"
  },
  {
    "title": "Pression du client plus intense",
    "weight": "1",
    "source": "https://reddit.com/comments/1r9n3ym"
  },
  {
    "title": "J’ai signé un contrat hier mais une offre plus intéressante vient de m’être faite aujourd’hui",
    "weight": "1",
    "source": "https://reddit.com/comments/1r7kea0"
  }
]